get_int/__init__.py
get_int/main.py
get_int-1.0.0.dist-info/LICENSE
get_int-1.0.0.dist-info/METADATA
get_int-1.0.0.dist-info/WHEEL
get_int-1.0.0.dist-info/top_level.txt
get_int-1.0.0.dist-info/RECORD
