Metadata-Version: 2.1
Name: get-int
Version: 1.0.0
Summary: easy_int_input
Home-page: https://github.com/themadbo1/get_int
Author: chungus.potato
Author-email: author@example.com
Project-URL: Bug Tracker, https://github.com/themadbo1/get_int/issues
Requires-Python: >=3.7
License-File: LICENSE
Requires-Dist: click
Requires-Dist: requests
Provides-Extra: testing
Requires-Dist: pytest ; extra == 'testing'
